chariots/__init__.py
chariots/_ml_mode.py
chariots/_op_store.py
chariots/_pipeline.py
chariots/cli.py
chariots/errors.py
chariots-0.2.4.dist-info/AUTHORS.rst
chariots-0.2.4.dist-info/LICENSE
chariots-0.2.4.dist-info/METADATA
chariots-0.2.4.dist-info/WHEEL
chariots-0.2.4.dist-info/entry_points.txt
chariots-0.2.4.dist-info/top_level.txt
chariots-0.2.4.dist-info/RECORD
