Metadata-Version: 2.1
Name: chariots
Version: 0.2.4
Summary: machine learning pipelines
Home-page: https://github.com/aredier/chariots
Author: Antoine Redier
Author-email: antoine.redier2@gmail.com
License: GNU General Public License v3
Keywords: chariots
Platform: UNKNOWN
Classifier: Development Status :: 3 - Alpha
Classifier: Intended Audience :: Developers
Classifier: License :: OSI Approved :: GNU General Public License v3 (GPLv3)
Classifier: Natural Language :: English
Classifier: Programming Language :: Python :: 3
Classifier: Programming Language :: Python :: 3.5
Classifier: Programming Language :: Python :: 3.6
Classifier: Programming Language :: Python :: 3.7
Requires-Dist: Click (>=6.0)
Requires-Dist: dill (==0.2.9)
Requires-Dist: flask (==1.0.3)
Requires-Dist: requests (==2.22.0)
Requires-Dist: cookiecutter (<2.0,>=1.6.0)
